 [

 {
"Name":"MMTVPN",
"Key":"",
"Valid":"365",
"Expiration":"31\/12\/2025"
},

 {
"Name":"DaLove",
"Key":"",
"Valid":"80",
"Expiration":"18\/11\/2025"
},

 {
"Name":"LynnKZ",
"Key":"",
"Valid":"75",
"Expiration":"16\/11\/2025"
},
  
 {
"Name":"တင်ဇာမိုး",
"Key":"d92f38d8cda17062",
"Valid":"70",
"Expiration":"17\/11\/2025"
},
 {
"Name":"ဟိန်းဖြိုးအောင်",
"Key":"63c87823e144bdaa",
"Valid":"32",
"Expiration":"09\/10\/2025"
}, 
  
 {
"Name":"စိုးသူ",
"Key":"ca2f11e72fe7b9de",
"Valid":"54",
"Expiration":"28\/10\/2025"
},

 {
"Name":"ပန်းကလေးနီ",
"Key":"",
"Valid":"77",
"Expiration":"25\/04\/2025"
},  
  
{
"Name":"သူရနိုင်",
"Key":"",
"Valid":"31",
"Expiration":"18\/03\/2025"
},
  
 {
"Name":"NawHsaLawEh",
"Key":"",
"Valid":"30",
"Expiration":"14\/03\/2025"
},
 {
"Name":"လရိတ်ခေတ်",
"Key":"",
"Valid":"30",
"Expiration":"11\/03\/2025"
},
{
"Name":"မင်းလေး",
"Key":"",
"Valid":"30",
"Expiration":"11\/03\/2025"
},
 {
"Name":"ကိုမင်း",
"Key":"",
"Valid":"30",
"Expiration":"03\/03\/2025"
},

{
"Name":"အောင်ငွေဝင်း",
"Key":"",
"Valid":"27",
"Expiration":"21\/02\/2025"
},
 
{
"Name":"Hast",
"Key":"",
"Valid":"32",
"Expiration":"16\/01\/2025"
},
{
"Name":"ဖွားဖွားပေါက်စ",
"Key":"",
"Valid":"30",
"Expiration":"04\/01\/2025"
}, 
{
"Name":"အောင်သော်တာ",
"Key":"",
"Valid":"30",
"Expiration":"04\/01\/2025"
}
  
  
]
