[

 {
"Name":"ရဲမင်းမင်း",
"Key":"19ccf99c91a46b0a",
"Valid":"365",
"Expiration":"14\/08\/2025"
},

 {
"Name":"စိုင်းစိုင်း",
"Key":"ec2783a3eb0c7cb9",
"Valid":"63",
"Expiration":"16\/10\/2024"
},

 {
"Name":"ဝေလွင့်ခြင်း",
"Key":"665c443773e9330e",
"Valid":"30",
"Expiration":"13\/09\/2024"
},

 {
"Name":"KoGyi",
"Key":"d24167de204ce4f2",
"Valid":"30",
"Expiration":"13\/09\/2024"
},
 
 {
"Name":"PaEhTharBom",
"Key":"cadd31621df5772f",
"Valid":"93",
"Expiration":"15\/11\/2024"
},

{
"Name":"ဇင်မီ",
"Key":"359dde66429d3c33",
"Valid":"17",
"Expiration":"31\/08\/2024"
},

 {
"Name":"လင်းအောင",
"Key":"05e8123506f6b04",
"Valid":"25",
"Expiration":"08\/09\/2024"
},

 {
"Name":"‌အောင်လေး",
"Key":"",
"Valid":"16",
"Expiration":"30\/08\/2024"
},

{
"Name":"Wpafc",
"Key":"afc0f480e8fbea12",
"Valid":"7",
"Expiration":"21\/08\/2024"
},

 {
"Name":"zinmar",
"Key":"",
"Valid":"8",
"Expiration":"22\/08\/2024"
},

{
"Name":"အေးအေး",
"Key":"",
"Valid":"20",
"Expiration":"03\/08\/2024"
},


 {
"Name":"ဝေယံဖြိုး",
"Key":"",
"Valid":"4",
"Expiration":"18\/08\/2024"
},
 
 {
"Name":"ချမ်းချမ်း",
"Key":"",
"Valid":"19",
"Expiration":"02\/09\/2024"
},

 {
"Name":"စိုးမင်းဦး",
"Key":"",
"Valid":"46",
"Expiration":"29\/09\/2024"
},

 {
"Name":"ချစ်လင်းဇော်",
"Key":"",
"Valid":"30",
"Expiration":"13\/09\/2024"
},

 {
"Name":"Justinrap",
"Key":"",
"Valid":"16",
"Expiration":"30\/08\/2024"
},

 {
"Name":"ဦးဖြိုး",
"Key":"",
"Valid":"27",
"Expiration":"10\/09\/2024"
},

 {
"Name":"‌ဦးအောင်လေး",
"Key":"",
"Valid":"13",
"Expiration":"27\/08\/2024"
},

 {
"Name":"မောင်ထွန်း",
"Key":"",
"Valid":"36",
"Expiration":"19\/09\/2024"
},

{
"Name":"မင်းအောင်",
"Key":"",
"Valid":"36",
"Expiration":"19\/09\/2024"
},
 
{
"Name":"SharKo",
"Key":"",
"Valid":"26",
"Expiration":"09\/09\/2024"
},
{
"Name":"ဇာဇာ",
"Key":"",
"Valid":"40",
"Expiration":"23\/09\/2024"
}
  
  
]
