[

 {
"Name":"MMTVPN",
"Key":"d535d5cc28c95b00",
"Valid":"365",
"Expiration":"23\/10\/2025"
},

 {
"Name":"ဖြိုးတေဇ",
"Key":"",
"Valid":"100",
"Expiration":"18\/01\/2025"
},

{
"Name":"ထက်အိ",
"Key":"49adb198e69f359d",
"Valid":"30",
"Expiration":"13\/11\/2024"
}, 

 {
"Name":"မင်းနိုင်ကျော်",
"Key":"",
"Valid":"70",
"Expiration":"21\/12\/2024"
},
 
 {
"Name":"စိုးစိုး",
"Key":"bca0916629ee4ca6",
"Valid":"30",
"Expiration":"13\/11\/2024"
},

{
"Name":"တင်ဦး",
"Key":"",
"Valid":"30",
"Expiration":"11\/11\/2024"
},

 {
"Name":"အေးအေး",
"Key":"",
"Valid":"32",
"Expiration":"14\/11\/2024"
},

 {
"Name":"‌HtetLinAung",
"Key":"",
"Valid":"30",
"Expiration":"05\/10\/2024"
},

{
"Name":"အောင်လေး",
"Key":"",
"Valid":"35",
"Expiration":"29\/10\/2024"
},

 {
"Name":"မောင်ထွန်း",
"Key":"",
"Valid":"36",
"Expiration":"19\/09\/2024"
},

{
"Name":"မင်းအောင်",
"Key":"",
"Valid":"36",
"Expiration":"19\/09\/2024"
},
 
{
"Name":"ဆုရီထွေး",
"Key":"",
"Valid":"7",
"Expiration":"22\/08\/2024"
},
{
"Name":"မောင်မြင့်ချို",
"Key":"",
"Valid":"16",
"Expiration":"31\/08\/2024"
}
  
  
]
